audio_preprocessing/__init__.py
audio_preprocessing/preprocess.py
audio_preprocessing/utils.py
childpro-0.1.dist-info/METADATA
childpro-0.1.dist-info/WHEEL
childpro-0.1.dist-info/entry_points.txt
childpro-0.1.dist-info/top_level.txt
childpro-0.1.dist-info/RECORD
