Metadata-Version: 2.4
Name: ChildPro
Version: 0.1
Summary: Audio Preprocessing Tool for ASR
Home-page: https://github.com/yourusername/ChildPro
Author: Your Name
Author-email: your-email@example.com
Classifier: Programming Language :: Python :: 3
Classifier: License :: OSI Approved :: MIT License
Classifier: Operating System :: OS Independent
Requires-Python: >=3.6
Requires-Dist: pydub
Requires-Dist: numpy
Dynamic: author
Dynamic: author-email
Dynamic: classifier
Dynamic: home-page
Dynamic: requires-dist
Dynamic: requires-python
Dynamic: summary
